llm_cmd_git/__init__.py
llm_cmd_git/cli.py
llm_cmd_git/git.py
llm_cmd_git/hooks.py
llm_cmd_git/settings.py
llm_cmd_git/prompts/__init__.py
llm_cmd_git/prompts/common.py
llm_cmd_git/prompts/conventional.py
llm_cmd_git/prompts/default.py
llm_cmd_git/prompts/odoo.py
llm_cmd_git-0.1.5.dist-info/METADATA
llm_cmd_git-0.1.5.dist-info/WHEEL
llm_cmd_git-0.1.5.dist-info/entry_points.txt
llm_cmd_git-0.1.5.dist-info/top_level.txt
llm_cmd_git-0.1.5.dist-info/RECORD
