Metadata-Version: 2.4
Name: llm-cmd-git
Version: 0.1.5
Summary: LLM plugin to enhance Git experience
Requires-Python: >=3.10
Requires-Dist: llm
Requires-Dist: pydanclick
Requires-Dist: pydantic-settings
Requires-Dist: questionary
Requires-Dist: rich-click
